[{"goals":1,"assists":0,"playerCode":"MADBOU","shotsOnGoals":0,"playerName":"MADJID BOUGHERRA","yellowCards":3,"gamesStarted":15,"shots":0,"substitute":0,"redCards":1,"foulsCommitted":0,"foulsSuffered":0},{"goals":8,"assists":0,"playerCode":"ISLSLI","shotsOnGoals":8,"playerName":"ISLAM SLIMANI","yellowCards":4,"gamesStarted":14,"shots":8,"substitute":15,"redCards":0,"foulsCommitted":0,"foulsSuffered":0},{"goals":0,"assists":0,"playerCode":"JAVMAS","shotsOnGoals":0,"playerName":"JAVIER MASCHERANO","yellowCards":0,"gamesStarted":0,"shots":0,"substitute":0,"redCards":0,"foulsCommitted":0,"foulsSuffered":0},{"goals":16,"assists":5,"playerCode":"TIMCAH","shotsOnGoals":29,"playerName":"TIM CAHILL","yellowCards":5,"gamesStarted":37,"shots":69,"substitute":2,"redCards":0,"foulsCommitted":100,"foulsSuffered":55},{"goals":1,"assists":0,"playerCode":"LUCNEI","shotsOnGoals":1,"playerName":"LUCAS NEILL","yellowCards":0,"gamesStarted":10,"shots":1,"substitute":1,"redCards":0,"foulsCommitted":7,"foulsSuffered":5},{"goals":0,"assists":0,"playerCode":"BREHOL","shotsOnGoals":0,"playerName":"BRETT HOLMAN","yellowCards":0,"gamesStarted":4,"shots":1,"substitute":0,"redCards":0,"foulsCommitted":2,"foulsSuffered":1},{"goals":61,"assists":0,"playerCode":"JULCES","shotsOnGoals":2,"playerName":"JULIO CESAR","yellowCards":1,"gamesStarted":22,"shots":1,"substitute":0,"redCards":0,"foulsCommitted":2,"foulsSuffered":3},{"goals":0,"assists":0,"playerCode":"ALESON","shotsOnGoals":0,"playerName":"ALEX SONG","yellowCards":0,"gamesStarted":0,"shots":0,"substitute":0,"redCards":0,"foulsCommitted":0,"foulsSuffered":0},{"goals":8,"assists":2,"playerCode":"EDUVAR","shotsOnGoals":24,"playerName":"EDUARDO VARGAS","yellowCards":2,"gamesStarted":22,"shots":55,"substitute":4,"redCards":0,"foulsCommitted":26,"foulsSuffered":40},{"goals":5,"assists":4,"playerCode":"MATFER","shotsOnGoals":25,"playerName":"MATIAS FERNANDEZ","yellowCards":3,"gamesStarted":31,"shots":51,"substitute":17,"redCards":0,"foulsCommitted":31,"foulsSuffered":56},{"goals":5,"assists":1,"playerCode":"TEOGUT","shotsOnGoals":19,"playerName":"TEO GUTIERREZ","yellowCards":2,"gamesStarted":15,"shots":30,"substitute":1,"redCards":0,"foulsCommitted":27,"foulsSuffered":13},{"goals":7,"assists":8,"playerCode":"BRYRUI","shotsOnGoals":16,"playerName":"BRYAN RUIZ","yellowCards":1,"gamesStarted":28,"shots":47,"substitute":6,"redCards":0,"foulsCommitted":18,"foulsSuffered":50},{"goals":17,"assists":2,"playerCode":"ALVSAB","shotsOnGoals":34,"playerName":"ALVARO SABORIO","yellowCards":6,"gamesStarted":30,"shots":94,"substitute":4,"redCards":0,"foulsCommitted":67,"foulsSuffered":35},{"goals":0,"assists":0,"playerCode":"DIDDRO","shotsOnGoals":0,"playerName":"DIDIER DROGBA","yellowCards":0,"gamesStarted":0,"shots":0,"substitute":0,"redCards":0,"foulsCommitted":0,"foulsSuffered":0},{"goals":0,"assists":0,"playerCode":"DARSRN","shotsOnGoals":0,"playerName":"DARIJO SRNA","yellowCards":0,"gamesStarted":0,"shots":0,"substitute":0,"redCards":0,"foulsCommitted":0,"foulsSuffered":0},{"goals":0,"assists":0,"playerCode":"EDU","shotsOnGoals":1,"playerName":"EDUARDO","yellowCards":1,"gamesStarted":3,"shots":4,"substitute":5,"redCards":0,"foulsCommitted":6,"foulsSuffered":2},{"goals":0,"assists":0,"playerCode":"ANTVAL","shotsOnGoals":0,"playerName":"ANTONIO VALENCIA","yellowCards":0,"gamesStarted":0,"shots":0,"substitute":0,"redCards":0,"foulsCommitted":0,"foulsSuffered":0},{"goals":7,"assists":0,"playerCode":"FELCAI","shotsOnGoals":7,"playerName":"FELIPE CAICEDO","yellowCards":3,"gamesStarted":16,"shots":19,"substitute":9,"redCards":0,"foulsCommitted":7,"foulsSuffered":7},{"goals":1,"assists":0,"playerCode":"EDIMEN","shotsOnGoals":1,"playerName":"EDISON MENDEZ","yellowCards":1,"gamesStarted":1,"shots":2,"substitute":1,"redCards":0,"foulsCommitted":1,"foulsSuffered":3},{"goals":0,"assists":0,"playerCode":"MICESS","shotsOnGoals":0,"playerName":"MICHAEL ESSIEN","yellowCards":0,"gamesStarted":0,"shots":0,"substitute":0,"redCards":0,"foulsCommitted":0,"foulsSuffered":0},{"goals":11,"assists":0,"playerCode":"ASAGYA","shotsOnGoals":8,"playerName":"ASAMOAH GYAN","yellowCards":0,"gamesStarted":13,"shots":9,"substitute":3,"redCards":0,"foulsCommitted":0,"foulsSuffered":0},{"goals":2,"assists":4,"playerCode":"GIOKAR","shotsOnGoals":8,"playerName":"GIORGOS KARAGOUNIS","yellowCards":6,"gamesStarted":17,"shots":27,"substitute":13,"redCards":0,"foulsCommitted":14,"foulsSuffered":67},{"goals":5,"assists":2,"playerCode":"DIMSAL","shotsOnGoals":6,"playerName":"DIMITRIOS SALPINGIDIS","yellowCards":2,"gamesStarted":8,"shots":13,"substitute":6,"redCards":0,"foulsCommitted":6,"foulsSuffered":16},{"goals":9,"assists":1,"playerCode":"MIT","shotsOnGoals":23,"playerName":"MITROGLOU","yellowCards":3,"gamesStarted":15,"shots":50,"substitute":1,"redCards":0,"foulsCommitted":14,"foulsSuffered":13},{"goals":0,"assists":10,"playerCode":"EMIIZA","shotsOnGoals":4,"playerName":"EMILIO IZAGUIRRE","yellowCards":8,"gamesStarted":46,"shots":16,"substitute":0,"redCards":0,"foulsCommitted":41,"foulsSuffered":29},{"goals":17,"assists":1,"playerCode":"NOEVAL","shotsOnGoals":0,"playerName":"NOEL VALLADARES","yellowCards":0,"gamesStarted":8,"shots":1,"substitute":0,"redCards":0,"foulsCommitted":0,"foulsSuffered":1},{"goals":0,"assists":0,"playerCode":"WILPAL","shotsOnGoals":0,"playerName":"WILSON PALACIOS","yellowCards":0,"gamesStarted":0,"shots":0,"substitute":0,"redCards":0,"foulsCommitted":0,"foulsSuffered":0},{"goals":0,"assists":0,"playerCode":"JAVNEK","shotsOnGoals":0,"playerName":"JAVAD NEKOUNAM","yellowCards":0,"gamesStarted":0,"shots":0,"substitute":0,"redCards":0,"foulsCommitted":0,"foulsSuffered":0},{"goals":1,"assists":0,"playerCode":"MASSHO","shotsOnGoals":0,"playerName":"MASOUD SHOJAEI","yellowCards":2,"gamesStarted":4,"shots":0,"substitute":0,"redCards":0,"foulsCommitted":0,"foulsSuffered":0},{"goals":5,"assists":1,"playerCode":"REZGHO","shotsOnGoals":10,"playerName":"REZA GHOOCHANNEJHAD","yellowCards":1,"gamesStarted":19,"shots":33,"substitute":10,"redCards":0,"foulsCommitted":9,"foulsSuffered":25},{"goals":6,"assists":3,"playerCode":"PABOSV","shotsOnGoals":20,"playerName":"PABLO OSVALDO","yellowCards":4,"gamesStarted":22,"shots":66,"substitute":12,"redCards":0,"foulsCommitted":41,"foulsSuffered":19},{"goals":12,"assists":4,"playerCode":"KEIHON","shotsOnGoals":16,"playerName":"KEISUKE HONDA","yellowCards":5,"gamesStarted":39,"shots":51,"substitute":5,"redCards":0,"foulsCommitted":19,"foulsSuffered":41},{"goals":0,"assists":0,"playerCode":"SHIKAG","shotsOnGoals":0,"playerName":"SHINJI KAGAWA","yellowCards":0,"gamesStarted":0,"shots":0,"substitute":0,"redCards":0,"foulsCommitted":0,"foulsSuffered":0},{"goals":3,"assists":0,"playerCode":"KIMSHI","shotsOnGoals":3,"playerName":"KIM SHINWOOK","yellowCards":1,"gamesStarted":10,"shots":5,"substitute":1,"redCards":0,"foulsCommitted":4,"foulsSuffered":1},{"goals":1,"assists":0,"playerCode":"LEEKEU","shotsOnGoals":1,"playerName":"LEE KEUNHO","yellowCards":0,"gamesStarted":5,"shots":3,"substitute":5,"redCards":0,"foulsCommitted":2,"foulsSuffered":4},{"goals":2,"assists":5,"playerCode":"LEECHU","shotsOnGoals":10,"playerName":"LEE CHUNGYONG","yellowCards":9,"gamesStarted":39,"shots":42,"substitute":15,"redCards":0,"foulsCommitted":42,"foulsSuffered":52},{"goals":0,"assists":2,"playerCode":"ANDGUA","shotsOnGoals":6,"playerName":"ANDRES GUARDADO","yellowCards":8,"gamesStarted":33,"shots":27,"substitute":6,"redCards":0,"foulsCommitted":49,"foulsSuffered":38},{"goals":35,"assists":9,"playerCode":"ORIPER","shotsOnGoals":86,"playerName":"ORIBE PERALTA","yellowCards":14,"gamesStarted":56,"shots":166,"substitute":2,"redCards":2,"foulsCommitted":132,"foulsSuffered":91},{"goals":4,"assists":2,"playerCode":"JERLEN","shotsOnGoals":8,"playerName":"JERMAINE LENS","yellowCards":3,"gamesStarted":18,"shots":24,"substitute":1,"redCards":1,"foulsCommitted":27,"foulsSuffered":14},{"goals":0,"assists":0,"playerCode":"NAN","shotsOnGoals":0,"playerName":"NANI","yellowCards":0,"gamesStarted":0,"shots":0,"substitute":0,"redCards":0,"foulsCommitted":0,"foulsSuffered":0},{"goals":0,"assists":0,"playerCode":"IGOAKI","shotsOnGoals":0,"playerName":"IGOR AKINFEEV","yellowCards":0,"gamesStarted":0,"shots":0,"substitute":0,"redCards":0,"foulsCommitted":0,"foulsSuffered":0},{"goals":6,"assists":2,"playerCode":"ROMSHI","shotsOnGoals":3,"playerName":"ROMAN SHIROKOV","yellowCards":4,"gamesStarted":21,"shots":15,"substitute":1,"redCards":0,"foulsCommitted":7,"foulsSuffered":15},{"goals":1,"assists":0,"playerCode":"VICFAY","shotsOnGoals":2,"playerName":"VICTOR FAYZULIN","yellowCards":2,"gamesStarted":14,"shots":14,"substitute":0,"redCards":0,"foulsCommitted":15,"foulsSuffered":22},{"goals":0,"assists":0,"playerCode":"CESFAB","shotsOnGoals":0,"playerName":"CESC FABREGAS","yellowCards":0,"gamesStarted":0,"shots":0,"substitute":0,"redCards":0,"foulsCommitted":0,"foulsSuffered":0},{"goals":0,"assists":0,"playerCode":"FABSCH","shotsOnGoals":0,"playerName":"FABIAN SCHAR","yellowCards":1,"gamesStarted":4,"shots":1,"substitute":0,"redCards":0,"foulsCommitted":1,"foulsSuffered":0},{"goals":4,"assists":0,"playerCode":"DIELUG","shotsOnGoals":9,"playerName":"DIEGO LUGANO","yellowCards":13,"gamesStarted":28,"shots":20,"substitute":2,"redCards":0,"foulsCommitted":51,"foulsSuffered":22},{"goals":0,"assists":0,"playerCode":"CLIDEM","shotsOnGoals":0,"playerName":"CLINT DEMPSEY","yellowCards":0,"gamesStarted":0,"shots":0,"substitute":0,"redCards":0,"foulsCommitted":0,"foulsSuffered":0},{"goals":3,"assists":3,"playerCode":"MICBRA","shotsOnGoals":3,"playerName":"MICHAEL BRADLEY","yellowCards":2,"gamesStarted":20,"shots":22,"substitute":6,"redCards":0,"foulsCommitted":23,"foulsSuffered":16}]